{"cameraMode":{"drawMode":0,"name":"Shaded","section":"Shading Mode"},"sceneLighting":true,"audioPlay":false,"sceneViewState":{"m_AlwaysRefresh":false,"showFog":true,"showSkybox":true,"showFlares":true,"showImageEffects":true,"showParticleSystems":true,"showVisualEffectGraphs":true,"m_FxEnabled":true},"in2DMode":false,"pivot":{"x":0.39158934354782107,"y":-0.707237720489502,"z":11.269791603088379},"rotation":{"x":0.3140914738178253,"y":-0.0008530181366950274,"z":0.000282307795714587,"w":0.9493926763534546},"size":4.694846153259277,"orthographic":false}